suggestions_matrecord/__init__.py
suggestions_matrecord/autocorrect book.txt
suggestions_matrecord/autocorrect.py
suggestions_matrecord-0.1.dist-info/LICENSE
suggestions_matrecord-0.1.dist-info/METADATA
suggestions_matrecord-0.1.dist-info/WHEEL
suggestions_matrecord-0.1.dist-info/top_level.txt
suggestions_matrecord-0.1.dist-info/RECORD
